picocolorsensor/__init__.py
picocolorsensor/_impl.cp39-win_amd64.pyd
picocolorsensor/_init_impl.py
picocolorsensor/pkgcfg.py
picocolorsensor/py.typed
picocolorsensor/version.py
picocolorsensor/__pycache__/__init__.cpython-39.pyc
picocolorsensor/__pycache__/_init_impl.cpython-39.pyc
picocolorsensor/__pycache__/version.cpython-39.pyc
picocolorsensor/_impl/__init__.pyi
picocolorsensor-2023.2.0.dist-info/METADATA
picocolorsensor-2023.2.0.dist-info/WHEEL
picocolorsensor-2023.2.0.dist-info/entry_points.txt
picocolorsensor-2023.2.0.dist-info/top_level.txt
picocolorsensor-2023.2.0.dist-info/RECORD
