Metadata-Version: 2.1
Name: picocolorsensor
Version: 2023.2.0
Summary: Use a REV Color Sensor V3 via Raspberry Pi Pico
Home-page: https://github.com/thedropbears/picocolorsensor
Author: David Vo
Author-email: david@thedropbears.org.au
License: BSD-3-Clause
Requires-Python: >=3.6
Requires-Dist: wpilib (<2024,>=2023.2.1)
